ds_extras/.DS_Store
ds_extras/__init__.py
ds_extras/analyticsds/__init__.py
ds_extras/analyticsds/admin.py
ds_extras/analyticsds/apps.py
ds_extras/analyticsds/models.py
ds_extras/analyticsds/migrations/__init__.py
ds_extras/analyticsds/templates/analyticsds.html
ds_extras/analyticsds/templatetags/__init__.py
ds_extras/analyticsds/templatetags/analyticsds_tags.py
ds_extras/calendards/.DS_Store
ds_extras/calendards/__init__.py
ds_extras/calendards/admin.py
ds_extras/calendards/apps.py
ds_extras/calendards/models.py
ds_extras/calendards/migrations/0001_initial.py
ds_extras/calendards/migrations/0002_event_delete_caldate.py
ds_extras/calendards/migrations/__init__.py
ds_extras/calendards/static/.DS_Store
ds_extras/calendards/static/calendards/.DS_Store
ds_extras/calendards/static/calendards/fullcalendar4/.DS_Store
ds_extras/calendards/static/calendards/fullcalendar4/packages/bootstrap/LICENSE.txt
ds_extras/calendards/static/calendards/fullcalendar4/packages/bootstrap/README.md
ds_extras/calendards/static/calendards/fullcalendar4/packages/bootstrap/main.css
ds_extras/calendards/static/calendards/fullcalendar4/packages/bootstrap/main.d.ts
ds_extras/calendards/static/calendards/fullcalendar4/packages/bootstrap/main.esm.js
ds_extras/calendards/static/calendards/fullcalendar4/packages/bootstrap/main.js
ds_extras/calendards/static/calendards/fullcalendar4/packages/bootstrap/main.min.css
ds_extras/calendards/static/calendards/fullcalendar4/packages/bootstrap/main.min.js
ds_extras/calendards/static/calendards/fullcalendar4/packages/bootstrap/package.json
ds_extras/calendards/static/calendards/fullcalendar4/packages/core/LICENSE.txt
ds_extras/calendards/static/calendards/fullcalendar4/packages/core/README.md
ds_extras/calendards/static/calendards/fullcalendar4/packages/core/locales-all.js
ds_extras/calendards/static/calendards/fullcalendar4/packages/core/locales-all.min.js
ds_extras/calendards/static/calendards/fullcalendar4/packages/core/main.css
ds_extras-0.3.1.dist-info/LICENSE
ds_extras-0.3.1.dist-info/WHEEL
ds_extras-0.3.1.dist-info/METADATA
ds_extras-0.3.1.dist-info/RECORD
