Metadata-Version: 2.1
Name: ds_extras
Version: 0.3.1
Summary: my demiansoft extras
Author-email: Hyungjin Kim <hj3415@gmail.com>
Classifier: License :: OSI Approved :: MIT License
Requires-Dist: Django >= 5.0.3
Requires-Dist: pillow >= 10.2.0
Project-URL: Home, https://www.demiansoft.com
